genesys/__init__.py
genesys/decorators.py
genesys/helpers.py
genesys_cli/__init__.py
genesys_cli/main.py
genesys_cli/scaffolding.py
genesys_cli/utils.py
genesys_cli/commands/__init__.py
genesys_cli/commands/build.py
genesys_cli/commands/doctor.py
genesys_cli/commands/launch.py
genesys_cli/commands/make.py
genesys_cli/commands/new.py
genesys_cli/commands/ros.py
genesys_cli/commands/rqt.py
genesys_cli/commands/run.py
genesys_cli/commands/sim.py
genesys_cli/commands/templates.py
genesys_framework_cli-0.1.5.dist-info/licenses/LICENSE.txt
genesys_framework_cli-0.1.5.dist-info/licenses/NOTICE.txt
genesys_framework_cli-0.1.5.dist-info/METADATA
genesys_framework_cli-0.1.5.dist-info/WHEEL
genesys_framework_cli-0.1.5.dist-info/entry_points.txt
genesys_framework_cli-0.1.5.dist-info/top_level.txt
genesys_framework_cli-0.1.5.dist-info/RECORD
