Metadata-Version: 2.4
Name: genesys_framework_cli
Version: 0.1.5
Summary: A developer-friendly, opinionated framework for ROS 2.
Author: Genesys Developer
Author-email: Chukwudulue Isaac <zikkychukwudulue@gmail.com>
Project-URL: Homepage, https://github.com/isaac-hash/Genesys.git
Project-URL: Issues, https://github.com/isaac-hash/Genesys/issues
Classifier: Programming Language :: Python :: 3
Classifier: License :: OSI Approved :: Apache Software License
Classifier: Operating System :: OS Independent
Requires-Python: >=3.8
License-File: LICENSE.txt
License-File: NOTICE.txt
Requires-Dist: click
Dynamic: author
Dynamic: license-file
